YuanmengXiangmuBijiWangzhuanJuejinShicaoXiangmuDianzishu180710/README.md
YuanmengXiangmuBijiWangzhuanJuejinShicaoXiangmuDianzishu180710/__init__.py
YuanmengXiangmuBijiWangzhuanJuejinShicaoXiangmuDianzishu180710/__main__.py
YuanmengXiangmuBijiWangzhuanJuejinShicaoXiangmuDianzishu180710/file.pdf
YuanmengXiangmuBijiWangzhuanJuejinShicaoXiangmuDianzishu180710/index.html
yuanmeng_xiangmu_biji_wangzhuan_juejin_shicao_xiangmu_dianzishu_180710-2024.3.5.0.dist-info/METADATA
yuanmeng_xiangmu_biji_wangzhuan_juejin_shicao_xiangmu_dianzishu_180710-2024.3.5.0.dist-info/WHEEL
yuanmeng_xiangmu_biji_wangzhuan_juejin_shicao_xiangmu_dianzishu_180710-2024.3.5.0.dist-info/entry_points.txt
yuanmeng_xiangmu_biji_wangzhuan_juejin_shicao_xiangmu_dianzishu_180710-2024.3.5.0.dist-info/top_level.txt
yuanmeng_xiangmu_biji_wangzhuan_juejin_shicao_xiangmu_dianzishu_180710-2024.3.5.0.dist-info/RECORD
